pyvalitron/__init__.py
pyvalitron/exceptions.py
pyvalitron/form.py
pyvalitron/sanitizer.py
pyvalitron/validator.py
pyvalitron-1.1.3.dist-info/LICENSE
pyvalitron-1.1.3.dist-info/METADATA
pyvalitron-1.1.3.dist-info/WHEEL
pyvalitron-1.1.3.dist-info/top_level.txt
pyvalitron-1.1.3.dist-info/RECORD
